autoembedder/__init__.py
autoembedder/data.py
autoembedder/evaluator.py
autoembedder/learner.py
autoembedder/model.py
autoembedder/training.py
autoembedder-0.2.5.dist-info/METADATA
autoembedder-0.2.5.dist-info/WHEEL
autoembedder-0.2.5.dist-info/LICENSE
autoembedder-0.2.5.dist-info/RECORD
