Metadata-Version: 2.1
Name: autoembedder
Version: 0.2.5
Summary: PyTorch autoencoder with additional embeddings layer for categorical data.
Home-page: https://chrislemke.github.io/autoembedder/
License: MIT
Keywords: autoencoder,embeddings,model,pytorch,neural network,machine learning,data science
Author: Christopher Lemke
Author-email: chris@syhbl.mozmail.com
Requires-Python: >=3.8,<3.11
Classifier: Intended Audience :: Science/Research
Classifier: License :: OSI Approved :: MIT License
Classifier: Programming Language :: Python :: 3
Classifier: Programming Language :: Python :: 3.8
Classifier: Programming Language :: Python :: 3.9
Classifier: Programming Language :: Python :: 3.10
Classifier: Topic :: Scientific/Engineering :: Artificial Intelligence
Classifier: Topic :: Scientific/Engineering :: Information Analysis
Requires-Dist: dask (==2022.12.0)
Requires-Dist: einops (>=0.6.0,<0.7.0)
Requires-Dist: fastparquet (==2022.12.0)
Requires-Dist: numpy (==1.24.1)
Requires-Dist: pandas (>=1.5.2,<2.0.0)
Requires-Dist: pytorch-ignite (>=0.4.10,<0.5.0)
Requires-Dist: tensorboard (==2.11.0)
Requires-Dist: torch (>=1.13.1,<2.0.0)
Requires-Dist: torchinfo (>=1.7.1,<2.0.0)
Requires-Dist: tqdm (>=4.64.1,<5.0.0)
Requires-Dist: typer (>=0.7.0,<0.8.0)
Project-URL: Documentation, https://chrislemke.github.io/autoembedder/
Project-URL: Repository, https://github.com/chrislemke/autoembedder
